{"313bc053d15a4e6340008dcf1a7048fd":{"statistic":{"failed":0,"broken":0,"skipped":0,"passed":1,"unknown":0,"total":1},"items":[{"uid":"d1c949140e0ccee6","reportUrl":"https://Rustam-Z.github.io/disney-test-api-taf/28//#testresult/d1c949140e0ccee6","status":"passed","time":{"start":1686279668629,"stop":1686279672971,"duration":4342}}]},"1ae16304988cdac5c19aee221d9b58b2":{"statistic":{"failed":0,"broken":1,"skipped":0,"passed":0,"unknown":0,"total":1},"items":[{"uid":"69b66eb8800df30a","reportUrl":"https://Rustam-Z.github.io/disney-test-api-taf/28//#testresult/69b66eb8800df30a","status":"broken","statusDetails":"pydantic.error_wrappers.ValidationError: 5 validation errors for CreateCartSuccessResponse\ndata -> id\n  field required (type=value_error.missing)\ndata -> created_at\n  field required (type=value_error.missing)\ndata -> updated_at\n  field required (type=value_error.missing)\ndata -> metro\n  field required (type=value_error.missing)\ndata -> metro_config\n  field required (type=value_error.missing)","time":{"start":1686279629680,"stop":1686279630295,"duration":615}}]},"18a1380028bf46edff4c226f2b7256d2":{"statistic":{"failed":0,"broken":0,"skipped":0,"passed":1,"unknown":0,"total":1},"items":[{"uid":"41f84dd4be5b6df9","reportUrl":"https://Rustam-Z.github.io/disney-test-api-taf/28//#testresult/41f84dd4be5b6df9","status":"passed","time":{"start":1686279705310,"stop":1686279705361,"duration":51}}]},"f975cbf51152f782f6cc288db63bc3d6":{"statistic":{"failed":0,"broken":0,"skipped":0,"passed":1,"unknown":0,"total":1},"items":[{"uid":"bc1b3a8c442562e8","reportUrl":"https://Rustam-Z.github.io/disney-test-api-taf/28//#testresult/bc1b3a8c442562e8","status":"passed","time":{"start":1686279551206,"stop":1686279551249,"duration":43}}]},"e8c778af0080cf4629b9b09e4ab68d3e":{"statistic":{"failed":0,"broken":0,"skipped":0,"passed":1,"unknown":0,"total":1},"items":[{"uid":"d8f33743a090618f","reportUrl":"https://Rustam-Z.github.io/disney-test-api-taf/28//#testresult/d8f33743a090618f","status":"passed","time":{"start":1686279551081,"stop":1686279551151,"duration":70}}]},"b717cbe48de7f5a56fe2126a674d1efc":{"statistic":{"failed":0,"broken":0,"skipped":0,"passed":1,"unknown":0,"total":1},"items":[{"uid":"3777cf9037e9e738","reportUrl":"https://Rustam-Z.github.io/disney-test-api-taf/28//#testresult/3777cf9037e9e738","status":"passed","time":{"start":1686279555504,"stop":1686279555550,"duration":46}}]},"af36fd39b258704352d2e982646ac258":{"statistic":{"failed":0,"broken":0,"skipped":0,"passed":1,"unknown":0,"total":1},"items":[{"uid":"d65a801c8c868b66","reportUrl":"https://Rustam-Z.github.io/disney-test-api-taf/28//#testresult/d65a801c8c868b66","status":"passed","time":{"start":1686279718230,"stop":1686279718289,"duration":59}}]},"8bfef7d8cf9d074604dc651bc881cd88":{"statistic":{"failed":0,"broken":0,"skipped":0,"passed":1,"unknown":0,"total":1},"items":[{"uid":"232c836cdcbe0208","reportUrl":"https://Rustam-Z.github.io/disney-test-api-taf/28//#testresult/232c836cdcbe0208","status":"passed","time":{"start":1686279691562,"stop":1686279691911,"duration":349}}]},"be2d7546f9bf20c33c86060eb1bae5ae":{"statistic":{"failed":0,"broken":0,"skipped":0,"passed":1,"unknown":0,"total":1},"items":[{"uid":"33eb3382b0922b92","reportUrl":"https://Rustam-Z.github.io/disney-test-api-taf/28//#testresult/33eb3382b0922b92","status":"passed","time":{"start":1686279706392,"stop":1686279706543,"duration":151}}]},"eb26fd032bf457c64326b464d67acbb3":{"statistic":{"failed":0,"broken":0,"skipped":0,"passed":1,"unknown":0,"total":1},"items":[{"uid":"1c57f35f36e570ba","reportUrl":"https://Rustam-Z.github.io/disney-test-api-taf/28//#testresult/1c57f35f36e570ba","status":"passed","time":{"start":1686279714384,"stop":1686279714401,"duration":17}}]},"e03bae8d3780c7ecf949eb5215e90e69":{"statistic":{"failed":0,"broken":0,"skipped":0,"passed":1,"unknown":0,"total":1},"items":[{"uid":"ade5913f3854b552","reportUrl":"https://Rustam-Z.github.io/disney-test-api-taf/28//#testresult/ade5913f3854b552","status":"passed","time":{"start":1686279690829,"stop":1686279691211,"duration":382}}]},"ed62a335b20480b779f96a09f6453ad2":{"statistic":{"failed":0,"broken":0,"skipped":0,"passed":1,"unknown":0,"total":1},"items":[{"uid":"a62abdc9c13cf9af","reportUrl":"https://Rustam-Z.github.io/disney-test-api-taf/28//#testresult/a62abdc9c13cf9af","status":"passed","time":{"start":1686279554564,"stop":1686279554766,"duration":202}}]},"2e1a41e15e264f118450df6aee39a091":{"statistic":{"failed":0,"broken":0,"skipped":0,"passed":1,"unknown":0,"total":1},"items":[{"uid":"bf97283ef7d1e340","reportUrl":"https://Rustam-Z.github.io/disney-test-api-taf/28//#testresult/bf97283ef7d1e340","status":"passed","time":{"start":1686279724209,"stop":1686279725722,"duration":1513}}]},"06949b58073337402cf0c0d9bde5c945":{"statistic":{"failed":0,"broken":1,"skipped":0,"passed":0,"unknown":0,"total":1},"items":[{"uid":"d233ef1f0bf3747e","reportUrl":"https://Rustam-Z.github.io/disney-test-api-taf/28//#testresult/d233ef1f0bf3747e","status":"broken","statusDetails":"pydantic.error_wrappers.ValidationError: 1 validation error for ErrorResponse\nmessage\n  message must be \"Error\" (type=value_error)","time":{"start":1686279703962,"stop":1686279704797,"duration":835}}]},"f2c125a842343766cb8046a26ac9997a":{"statistic":{"failed":0,"broken":0,"skipped":0,"passed":1,"unknown":0,"total":1},"items":[{"uid":"d9d8d52661e2c6e4","reportUrl":"https://Rustam-Z.github.io/disney-test-api-taf/28//#testresult/d9d8d52661e2c6e4","status":"passed","time":{"start":1686279545140,"stop":1686279546158,"duration":1018}}]},"02ad2684e0bc116610edb1047a7d6b4c":{"statistic":{"failed":0,"broken":0,"skipped":0,"passed":1,"unknown":0,"total":1},"items":[{"uid":"6b9d38fc918ee590","reportUrl":"https://Rustam-Z.github.io/disney-test-api-taf/28//#testresult/6b9d38fc918ee590","status":"passed","time":{"start":1686279533550,"stop":1686279533692,"duration":142}}]},"7f21eeadd8a1231893f28fc6fe2ae940":{"statistic":{"failed":0,"broken":0,"skipped":0,"passed":1,"unknown":0,"total":1},"items":[{"uid":"567acbfa15d6db54","reportUrl":"https://Rustam-Z.github.io/disney-test-api-taf/28//#testresult/567acbfa15d6db54","status":"passed","time":{"start":1686279552988,"stop":1686279553253,"duration":265}}]},"a1507f03d5f40c2b4e2ba425fac34adc":{"statistic":{"failed":0,"broken":0,"skipped":0,"passed":1,"unknown":0,"total":1},"items":[{"uid":"8599e20dfbdf6fd3","reportUrl":"https://Rustam-Z.github.io/disney-test-api-taf/28//#testresult/8599e20dfbdf6fd3","status":"passed","time":{"start":1686279534050,"stop":1686279534265,"duration":215}}]},"d2f74da5a64fda680e045433e28c9f4c":{"statistic":{"failed":0,"broken":0,"skipped":0,"passed":1,"unknown":0,"total":1},"items":[{"uid":"66fe4dd6fbb87edc","reportUrl":"https://Rustam-Z.github.io/disney-test-api-taf/28//#testresult/66fe4dd6fbb87edc","status":"passed","time":{"start":1686279634027,"stop":1686279634238,"duration":211}}]},"45c86c8eb9c7e2dd745d22848da2e2e7":{"statistic":{"failed":0,"broken":0,"skipped":0,"passed":1,"unknown":0,"total":1},"items":[{"uid":"658ceee0b4e7100","reportUrl":"https://Rustam-Z.github.io/disney-test-api-taf/28//#testresult/658ceee0b4e7100","status":"passed","time":{"start":1686279722129,"stop":1686279723741,"duration":1612}}]},"1caf32a888c758333961d22dddd918db":{"statistic":{"failed":0,"broken":0,"skipped":0,"passed":1,"unknown":0,"total":1},"items":[{"uid":"2797c2127ff5f306","reportUrl":"https://Rustam-Z.github.io/disney-test-api-taf/28//#testresult/2797c2127ff5f306","status":"passed","time":{"start":1686279535288,"stop":1686279535347,"duration":59}}]},"fefc8f4fb96765d8ff5ebab872f62e9f":{"statistic":{"failed":0,"broken":0,"skipped":0,"passed":1,"unknown":0,"total":1},"items":[{"uid":"aa108306368b2738","reportUrl":"https://Rustam-Z.github.io/disney-test-api-taf/28//#testresult/aa108306368b2738","status":"passed","time":{"start":1686279559095,"stop":1686279559300,"duration":205}}]},"b50a91e8c656cb39c6885b0585203dac":{"statistic":{"failed":0,"broken":0,"skipped":0,"passed":1,"unknown":0,"total":1},"items":[{"uid":"b7cfb1d0f22034ff","reportUrl":"https://Rustam-Z.github.io/disney-test-api-taf/28//#testresult/b7cfb1d0f22034ff","status":"passed","time":{"start":1686279691495,"stop":1686279691559,"duration":64}}]},"913c7641ed2f67f0a44ba15365dd0813":{"statistic":{"failed":0,"broken":0,"skipped":0,"passed":1,"unknown":0,"total":1},"items":[{"uid":"33f120490a5d9e1b","reportUrl":"https://Rustam-Z.github.io/disney-test-api-taf/28//#testresult/33f120490a5d9e1b","status":"passed","time":{"start":1686279533459,"stop":1686279533547,"duration":88}}]},"cebf2f1fd7a05fbfc3f1f2b2a70f4e3b":{"statistic":{"failed":0,"broken":0,"skipped":0,"passed":1,"unknown":0,"total":1},"items":[{"uid":"fd0d9b708a56ccfb","reportUrl":"https://Rustam-Z.github.io/disney-test-api-taf/28//#testresult/fd0d9b708a56ccfb","status":"passed","time":{"start":1686279548737,"stop":1686279548963,"duration":226}}]},"daf4b92f57ecec300477624017d85e9a":{"statistic":{"failed":0,"broken":0,"skipped":0,"passed":1,"unknown":0,"total":1},"items":[{"uid":"53a6a5097af3aea7","reportUrl":"https://Rustam-Z.github.io/disney-test-api-taf/28//#testresult/53a6a5097af3aea7","status":"passed","time":{"start":1686279557326,"stop":1686279557581,"duration":255}}]},"f53bf5af7970821810f2bd0cdfe26cf7":{"statistic":{"failed":0,"broken":0,"skipped":0,"passed":1,"unknown":0,"total":1},"items":[{"uid":"b5353df1bedc0f4b","reportUrl":"https://Rustam-Z.github.io/disney-test-api-taf/28//#testresult/b5353df1bedc0f4b","status":"passed","time":{"start":1686279536214,"stop":1686279536473,"duration":259}}]},"3833de2f2c477b93117069cac0059e20":{"statistic":{"failed":0,"broken":0,"skipped":1,"passed":0,"unknown":0,"total":1},"items":[{"uid":"ef8e6877612a5142","reportUrl":"https://Rustam-Z.github.io/disney-test-api-taf/28//#testresult/ef8e6877612a5142","status":"skipped","statusDetails":"Skipped: Need to investigate why the test fails.","time":{"start":1686279634332,"stop":1686279634332,"duration":0}}]},"7b56c52d740d781edf22d89afcec05c3":{"statistic":{"failed":0,"broken":0,"skipped":0,"passed":1,"unknown":0,"total":1},"items":[{"uid":"2506d7dda3a61131","reportUrl":"https://Rustam-Z.github.io/disney-test-api-taf/28//#testresult/2506d7dda3a61131","status":"passed","time":{"start":1686279715188,"stop":1686279716416,"duration":1228}}]},"3feaf46d2ac14abbefca166f9a53cc51":{"statistic":{"failed":0,"broken":0,"skipped":0,"passed":1,"unknown":0,"total":1},"items":[{"uid":"131f695c97213363","reportUrl":"https://Rustam-Z.github.io/disney-test-api-taf/28//#testresult/131f695c97213363","status":"passed","time":{"start":1686279690209,"stop":1686279690331,"duration":122}}]},"802d6da71f0b85ce90c01129a5100b24":{"statistic":{"failed":0,"broken":0,"skipped":0,"passed":1,"unknown":0,"total":1},"items":[{"uid":"d48402ce0c6b1d3d","reportUrl":"https://Rustam-Z.github.io/disney-test-api-taf/28//#testresult/d48402ce0c6b1d3d","status":"passed","time":{"start":1686279694790,"stop":1686279695643,"duration":853}}]},"91e7d554234e1f1da237437947c7a248":{"statistic":{"failed":0,"broken":0,"skipped":0,"passed":1,"unknown":0,"total":1},"items":[{"uid":"799731fd622efea7","reportUrl":"https://Rustam-Z.github.io/disney-test-api-taf/28//#testresult/799731fd622efea7","status":"passed","time":{"start":1686279543630,"stop":1686279543681,"duration":51}}]},"0505eae8f26eb8e7f28a4d487e301527":{"statistic":{"failed":0,"broken":0,"skipped":0,"passed":1,"unknown":0,"total":1},"items":[{"uid":"2af97b5456b88171","reportUrl":"https://Rustam-Z.github.io/disney-test-api-taf/28//#testresult/2af97b5456b88171","status":"passed","time":{"start":1686279535598,"stop":1686279535635,"duration":37}}]},"e645e4a241fb6f617ecef2efe27b7653":{"statistic":{"failed":0,"broken":0,"skipped":0,"passed":1,"unknown":0,"total":1},"items":[{"uid":"2750d724b548943e","reportUrl":"https://Rustam-Z.github.io/disney-test-api-taf/28//#testresult/2750d724b548943e","status":"passed","time":{"start":1686279550060,"stop":1686279550197,"duration":137}}]},"ec4190c5ba36144515b646e6bb294dde":{"statistic":{"failed":0,"broken":0,"skipped":0,"passed":1,"unknown":0,"total":1},"items":[{"uid":"ecb9aebaac4c16f9","reportUrl":"https://Rustam-Z.github.io/disney-test-api-taf/28//#testresult/ecb9aebaac4c16f9","status":"passed","time":{"start":1686279646810,"stop":1686279646899,"duration":89}}]},"fe9a36d7b34109daf12f0ed61e6f1821":{"statistic":{"failed":0,"broken":0,"skipped":0,"passed":1,"unknown":0,"total":1},"items":[{"uid":"b570f9f00e0c0bf9","reportUrl":"https://Rustam-Z.github.io/disney-test-api-taf/28//#testresult/b570f9f00e0c0bf9","status":"passed","time":{"start":1686279625631,"stop":1686279626330,"duration":699}}]},"4cb166cde80077a8758f651eae1e4aac":{"statistic":{"failed":0,"broken":0,"skipped":0,"passed":1,"unknown":0,"total":1},"items":[{"uid":"122c9e47d0d89189","reportUrl":"https://Rustam-Z.github.io/disney-test-api-taf/28//#testresult/122c9e47d0d89189","status":"passed","time":{"start":1686279532617,"stop":1686279532714,"duration":97}}]},"c28bfadf9e50e4af0dcbc956ca903486":{"statistic":{"failed":0,"broken":0,"skipped":1,"passed":0,"unknown":0,"total":1},"items":[{"uid":"ceb57d484afafb41","reportUrl":"https://Rustam-Z.github.io/disney-test-api-taf/28//#testresult/ceb57d484afafb41","status":"skipped","statusDetails":"Skipped: From where the order is being fetched?","time":{"start":1686279542210,"stop":1686279542210,"duration":0}}]},"e96bef755ce359c3b95ec6352f6327ca":{"statistic":{"failed":0,"broken":0,"skipped":0,"passed":1,"unknown":0,"total":1},"items":[{"uid":"963baca23e33e1f8","reportUrl":"https://Rustam-Z.github.io/disney-test-api-taf/28//#testresult/963baca23e33e1f8","status":"passed","time":{"start":1686279635579,"stop":1686279635629,"duration":50}}]},"3ecc22dbdbd7438352294dc74c2cf954":{"statistic":{"failed":0,"broken":0,"skipped":0,"passed":1,"unknown":0,"total":1},"items":[{"uid":"f86bfff78e42d692","reportUrl":"https://Rustam-Z.github.io/disney-test-api-taf/28//#testresult/f86bfff78e42d692","status":"passed","time":{"start":1686279555036,"stop":1686279555236,"duration":200}}]},"b8143c83261f9ed399dc2ea01ca8a6c6":{"statistic":{"failed":0,"broken":0,"skipped":0,"passed":1,"unknown":0,"total":1},"items":[{"uid":"e9854a460380b8f3","reportUrl":"https://Rustam-Z.github.io/disney-test-api-taf/28//#testresult/e9854a460380b8f3","status":"passed","time":{"start":1686279550896,"stop":1686279550951,"duration":55}}]},"4a9e09e389c6dcb36fef0a385d7452fd":{"statistic":{"failed":0,"broken":0,"skipped":0,"passed":1,"unknown":0,"total":1},"items":[{"uid":"74621889cd12442e","reportUrl":"https://Rustam-Z.github.io/disney-test-api-taf/28//#testresult/74621889cd12442e","status":"passed","time":{"start":1686279714422,"stop":1686279714794,"duration":372}}]},"0d93abbd22d0c4081045fffa155e6e5a":{"statistic":{"failed":0,"broken":0,"skipped":0,"passed":1,"unknown":0,"total":1},"items":[{"uid":"b765820b84f0a8b3","reportUrl":"https://Rustam-Z.github.io/disney-test-api-taf/28//#testresult/b765820b84f0a8b3","status":"passed","time":{"start":1686279709816,"stop":1686279710479,"duration":663}}]},"2a1530fd3c5cd6c173e946e3be7969d0":{"statistic":{"failed":0,"broken":0,"skipped":0,"passed":1,"unknown":0,"total":1},"items":[{"uid":"c5d1a7c6e9389bd5","reportUrl":"https://Rustam-Z.github.io/disney-test-api-taf/28//#testresult/c5d1a7c6e9389bd5","status":"passed","time":{"start":1686279537827,"stop":1686279538042,"duration":215}}]},"4b904e66b6c9363619eb7990ef2d4648":{"statistic":{"failed":0,"broken":0,"skipped":0,"passed":1,"unknown":0,"total":1},"items":[{"uid":"6c838ec22f8def84","reportUrl":"https://Rustam-Z.github.io/disney-test-api-taf/28//#testresult/6c838ec22f8def84","status":"passed","time":{"start":1686279535152,"stop":1686279535167,"duration":15}}]},"2e54bea542ac1a8710f3e133ae839f01":{"statistic":{"failed":0,"broken":0,"skipped":0,"passed":1,"unknown":0,"total":1},"items":[{"uid":"24fde48dd8f56822","reportUrl":"https://Rustam-Z.github.io/disney-test-api-taf/28//#testresult/24fde48dd8f56822","status":"passed","time":{"start":1686279538299,"stop":1686279538361,"duration":62}}]},"f5e7b0d481bb5b9132f3cd9bde090c73":{"statistic":{"failed":0,"broken":0,"skipped":0,"passed":1,"unknown":0,"total":1},"items":[{"uid":"c21cc5ef56dd0846","reportUrl":"https://Rustam-Z.github.io/disney-test-api-taf/28//#testresult/c21cc5ef56dd0846","status":"passed","time":{"start":1686279712608,"stop":1686279712967,"duration":359}}]},"22cf59b21407204d88d097fc718c79ec":{"statistic":{"failed":0,"broken":0,"skipped":0,"passed":1,"unknown":0,"total":1},"items":[{"uid":"e6c14d88ea533685","reportUrl":"https://Rustam-Z.github.io/disney-test-api-taf/28//#testresult/e6c14d88ea533685","status":"passed","time":{"start":1686279539437,"stop":1686279539794,"duration":357}}]},"8570143ea26ff4499db5653d7688f9b3":{"statistic":{"failed":0,"broken":0,"skipped":0,"passed":1,"unknown":0,"total":1},"items":[{"uid":"f78befd32e532d0f","reportUrl":"https://Rustam-Z.github.io/disney-test-api-taf/28//#testresult/f78befd32e532d0f","status":"passed","time":{"start":1686279535454,"stop":1686279535509,"duration":55}}]},"70d9fded2568c8991c109699e1f2f86b":{"statistic":{"failed":0,"broken":0,"skipped":0,"passed":1,"unknown":0,"total":1},"items":[{"uid":"31a399430032aaa8","reportUrl":"https://Rustam-Z.github.io/disney-test-api-taf/28//#testresult/31a399430032aaa8","status":"passed","time":{"start":1686279638872,"stop":1686279640524,"duration":1652}}]},"2a56c4d2d3c9f429308434e09d20b2d1":{"statistic":{"failed":0,"broken":0,"skipped":0,"passed":1,"unknown":0,"total":1},"items":[{"uid":"dbca329cb57ca289","reportUrl":"https://Rustam-Z.github.io/disney-test-api-taf/28//#testresult/dbca329cb57ca289","status":"passed","time":{"start":1686279538903,"stop":1686279539181,"duration":278}}]},"31ac5d4edd0c9d4acf0b7c79f5a077a7":{"statistic":{"failed":0,"broken":0,"skipped":0,"passed":1,"unknown":0,"total":1},"items":[{"uid":"6039fce91d664ed6","reportUrl":"https://Rustam-Z.github.io/disney-test-api-taf/28//#testresult/6039fce91d664ed6","status":"passed","time":{"start":1686279542214,"stop":1686279542269,"duration":55}}]},"400f2e13dab67a65040ef2ca65146254":{"statistic":{"failed":0,"broken":0,"skipped":0,"passed":1,"unknown":0,"total":1},"items":[{"uid":"2b857af3d9d6eedc","reportUrl":"https://Rustam-Z.github.io/disney-test-api-taf/28//#testresult/2b857af3d9d6eedc","status":"passed","time":{"start":1686279535170,"stop":1686279535183,"duration":13}}]},"0a74eb14d6e0ed5954074039f09f9430":{"statistic":{"failed":0,"broken":0,"skipped":0,"passed":1,"unknown":0,"total":1},"items":[{"uid":"ae4e77e789c72be5","reportUrl":"https://Rustam-Z.github.io/disney-test-api-taf/28//#testresult/ae4e77e789c72be5","status":"passed","time":{"start":1686279707631,"stop":1686279708166,"duration":535}}]},"d49961b7a037669c2d4824aad9d83825":{"statistic":{"failed":0,"broken":0,"skipped":0,"passed":1,"unknown":0,"total":1},"items":[{"uid":"9fdc7462cd135cae","reportUrl":"https://Rustam-Z.github.io/disney-test-api-taf/28//#testresult/9fdc7462cd135cae","status":"passed","time":{"start":1686279558842,"stop":1686279558972,"duration":130}}]},"1c97d0640f8bb2e3a6c8332f78c4c2b6":{"statistic":{"failed":0,"broken":0,"skipped":0,"passed":1,"unknown":0,"total":1},"items":[{"uid":"d0056ebfb53b5f2f","reportUrl":"https://Rustam-Z.github.io/disney-test-api-taf/28//#testresult/d0056ebfb53b5f2f","status":"passed","time":{"start":1686279550676,"stop":1686279550843,"duration":167}}]},"477ce7a474540a04dfad130240734921":{"statistic":{"failed":0,"broken":0,"skipped":0,"passed":1,"unknown":0,"total":1},"items":[{"uid":"d903350668b7b52f","reportUrl":"https://Rustam-Z.github.io/disney-test-api-taf/28//#testresult/d903350668b7b52f","status":"passed","time":{"start":1686279535118,"stop":1686279535133,"duration":15}}]},"2e4f71494b3225b454aa7f61bf9123bc":{"statistic":{"failed":0,"broken":0,"skipped":0,"passed":1,"unknown":0,"total":1},"items":[{"uid":"1fecd2ec688d378d","reportUrl":"https://Rustam-Z.github.io/disney-test-api-taf/28//#testresult/1fecd2ec688d378d","status":"passed","time":{"start":1686279558530,"stop":1686279558594,"duration":64}}]},"3d87df4cdd55fb99447257522e304da5":{"statistic":{"failed":0,"broken":0,"skipped":0,"passed":1,"unknown":0,"total":1},"items":[{"uid":"8ecebb3b24f03ec3","reportUrl":"https://Rustam-Z.github.io/disney-test-api-taf/28//#testresult/8ecebb3b24f03ec3","status":"passed","time":{"start":1686279706103,"stop":1686279706292,"duration":189}}]},"afbce948b0584a91fe747aa81ed32fd3":{"statistic":{"failed":0,"broken":0,"skipped":0,"passed":1,"unknown":0,"total":1},"items":[{"uid":"64f400e36eee6a32","reportUrl":"https://Rustam-Z.github.io/disney-test-api-taf/28//#testresult/64f400e36eee6a32","status":"passed","time":{"start":1686279548416,"stop":1686279548556,"duration":140}}]},"1befe6020f3e21ddacedbc1913309cbc":{"statistic":{"failed":0,"broken":0,"skipped":0,"passed":1,"unknown":0,"total":1},"items":[{"uid":"5bbc13bff1a306f0","reportUrl":"https://Rustam-Z.github.io/disney-test-api-taf/28//#testresult/5bbc13bff1a306f0","status":"passed","time":{"start":1686279636023,"stop":1686279636074,"duration":51}}]},"440f7a31f35d8d35226260fcfc7d7432":{"statistic":{"failed":0,"broken":0,"skipped":0,"passed":1,"unknown":0,"total":1},"items":[{"uid":"76b98e58cfd7d98f","reportUrl":"https://Rustam-Z.github.io/disney-test-api-taf/28//#testresult/76b98e58cfd7d98f","status":"passed","time":{"start":1686279551012,"stop":1686279551027,"duration":15}}]},"0ae263237200f0f027b0958d2c941b1f":{"statistic":{"failed":0,"broken":0,"skipped":0,"passed":1,"unknown":0,"total":1},"items":[{"uid":"520359d0df4005e2","reportUrl":"https://Rustam-Z.github.io/disney-test-api-taf/28//#testresult/520359d0df4005e2","status":"passed","time":{"start":1686279636077,"stop":1686279636340,"duration":263}}]},"a30ae6654990426dea08821b20588edb":{"statistic":{"failed":0,"broken":0,"skipped":0,"passed":1,"unknown":0,"total":1},"items":[{"uid":"11a707c48fce466f","reportUrl":"https://Rustam-Z.github.io/disney-test-api-taf/28//#testresult/11a707c48fce466f","status":"passed","time":{"start":1686279690333,"stop":1686279690613,"duration":280}}]},"d1eb6d31842670e1177b9d3b9d2aa6e7":{"statistic":{"failed":0,"broken":0,"skipped":0,"passed":1,"unknown":0,"total":1},"items":[{"uid":"d3b04f808990d023","reportUrl":"https://Rustam-Z.github.io/disney-test-api-taf/28//#testresult/d3b04f808990d023","status":"passed","time":{"start":1686279649357,"stop":1686279656928,"duration":7571}}]},"5a62ff28e13ce8c33d6d6e65ef527452":{"statistic":{"failed":0,"broken":0,"skipped":0,"passed":1,"unknown":0,"total":1},"items":[{"uid":"a2e08ff0e56cba93","reportUrl":"https://Rustam-Z.github.io/disney-test-api-taf/28//#testresult/a2e08ff0e56cba93","status":"passed","time":{"start":1686279534584,"stop":1686279534634,"duration":50}}]},"a46b3eb3e8b07b26ed276c696ee9998d":{"statistic":{"failed":0,"broken":0,"skipped":0,"passed":1,"unknown":0,"total":1},"items":[{"uid":"b20889a667218ef6","reportUrl":"https://Rustam-Z.github.io/disney-test-api-taf/28//#testresult/b20889a667218ef6","status":"passed","time":{"start":1686279633422,"stop":1686279633724,"duration":302}}]},"614c9f63b7ff942f3802ec04626f5345":{"statistic":{"failed":0,"broken":0,"skipped":0,"passed":1,"unknown":0,"total":1},"items":[{"uid":"52b648dbf87cac9","reportUrl":"https://Rustam-Z.github.io/disney-test-api-taf/28//#testresult/52b648dbf87cac9","status":"passed","time":{"start":1686279533209,"stop":1686279533363,"duration":154}}]},"cb4cb83fc4f16c439f7639abec83cd07":{"statistic":{"failed":0,"broken":0,"skipped":0,"passed":1,"unknown":0,"total":1},"items":[{"uid":"865ed4c384044d8d","reportUrl":"https://Rustam-Z.github.io/disney-test-api-taf/28//#testresult/865ed4c384044d8d","status":"passed","time":{"start":1686279706704,"stop":1686279707075,"duration":371}}]},"e41f52d85375d9a942e9fd8eff9c37d8":{"statistic":{"failed":0,"broken":0,"skipped":0,"passed":1,"unknown":0,"total":1},"items":[{"uid":"624800b2172e430c","reportUrl":"https://Rustam-Z.github.io/disney-test-api-taf/28//#testresult/624800b2172e430c","status":"passed","time":{"start":1686279708842,"stop":1686279709740,"duration":898}}]},"de628dcecd578e0f1ed0aabce31b194f":{"statistic":{"failed":0,"broken":0,"skipped":0,"passed":1,"unknown":0,"total":1},"items":[{"uid":"1760ce69255c6ed6","reportUrl":"https://Rustam-Z.github.io/disney-test-api-taf/28//#testresult/1760ce69255c6ed6","status":"passed","time":{"start":1686279705364,"stop":1686279705839,"duration":475}}]},"7d9a3e147824fb73d94ae75e0917ae99":{"statistic":{"failed":0,"broken":0,"skipped":0,"passed":1,"unknown":0,"total":1},"items":[{"uid":"4aac088446fd94fe","reportUrl":"https://Rustam-Z.github.io/disney-test-api-taf/28//#testresult/4aac088446fd94fe","status":"passed","time":{"start":1686279550995,"stop":1686279551010,"duration":15}}]},"67c2e1ca70e9cde1f9cb02d0e3c69b46":{"statistic":{"failed":0,"broken":0,"skipped":0,"passed":1,"unknown":0,"total":1},"items":[{"uid":"eb123f2b5dfbbde9","reportUrl":"https://Rustam-Z.github.io/disney-test-api-taf/28//#testresult/eb123f2b5dfbbde9","status":"passed","time":{"start":1686279705265,"stop":1686279705307,"duration":42}}]},"bb646c22c55a856b042d4a43969406d5":{"statistic":{"failed":0,"broken":0,"skipped":0,"passed":1,"unknown":0,"total":1},"items":[{"uid":"eeb1cbf327c04087","reportUrl":"https://Rustam-Z.github.io/disney-test-api-taf/28//#testresult/eeb1cbf327c04087","status":"passed","time":{"start":1686279532960,"stop":1686279533100,"duration":140}}]},"a9bab215f3711bb56c6da29986ee30a6":{"statistic":{"failed":0,"broken":0,"skipped":0,"passed":1,"unknown":0,"total":1},"items":[{"uid":"6596e8ba8c5af801","reportUrl":"https://Rustam-Z.github.io/disney-test-api-taf/28//#testresult/6596e8ba8c5af801","status":"passed","time":{"start":1686279532718,"stop":1686279532858,"duration":140}}]},"53efa2812c3fd2a010bc217703318970":{"statistic":{"failed":0,"broken":0,"skipped":0,"passed":1,"unknown":0,"total":1},"items":[{"uid":"8777bc15442e463a","reportUrl":"https://Rustam-Z.github.io/disney-test-api-taf/28//#testresult/8777bc15442e463a","status":"passed","time":{"start":1686279535016,"stop":1686279535100,"duration":84}}]},"fbf3ab27d225e21576ae708649db560d":{"statistic":{"failed":0,"broken":0,"skipped":0,"passed":1,"unknown":0,"total":1},"items":[{"uid":"77e97acde501e9a9","reportUrl":"https://Rustam-Z.github.io/disney-test-api-taf/28//#testresult/77e97acde501e9a9","status":"passed","time":{"start":1686279551252,"stop":1686279551288,"duration":36}}]},"5cb40a3004f44633e6f1039e809c7e80":{"statistic":{"failed":0,"broken":0,"skipped":0,"passed":1,"unknown":0,"total":1},"items":[{"uid":"c3b933ca77a3e4c5","reportUrl":"https://Rustam-Z.github.io/disney-test-api-taf/28//#testresult/c3b933ca77a3e4c5","status":"passed","time":{"start":1686279635632,"stop":1686279635825,"duration":193}}]},"3e9cac824ccb5744aee088ad8a80d4b9":{"statistic":{"failed":0,"broken":0,"skipped":0,"passed":1,"unknown":0,"total":1},"items":[{"uid":"5f23ef8071a2511d","reportUrl":"https://Rustam-Z.github.io/disney-test-api-taf/28//#testresult/5f23ef8071a2511d","status":"passed","time":{"start":1686279549584,"stop":1686279549708,"duration":124}}]},"bfc04f4cd216f58eff8a72dace855000":{"statistic":{"failed":0,"broken":0,"skipped":0,"passed":1,"unknown":0,"total":1},"items":[{"uid":"3b6e02b76da08e57","reportUrl":"https://Rustam-Z.github.io/disney-test-api-taf/28//#testresult/3b6e02b76da08e57","status":"passed","time":{"start":1686279641245,"stop":1686279642704,"duration":1459}}]},"caa8954574f6cf10a54cccab5e123364":{"statistic":{"failed":0,"broken":0,"skipped":0,"passed":1,"unknown":0,"total":1},"items":[{"uid":"6107899f0b7b2d9d","reportUrl":"https://Rustam-Z.github.io/disney-test-api-taf/28//#testresult/6107899f0b7b2d9d","status":"passed","time":{"start":1686279536138,"stop":1686279536211,"duration":73}}]},"c3d580df2052ff8afc00607ead68bfbd":{"statistic":{"failed":0,"broken":0,"skipped":0,"passed":1,"unknown":0,"total":1},"items":[{"uid":"66494fed7f4ad9a4","reportUrl":"https://Rustam-Z.github.io/disney-test-api-taf/28//#testresult/66494fed7f4ad9a4","status":"passed","time":{"start":1686279542272,"stop":1686279543220,"duration":948}}]},"50ce09ee8194928fc5c67fa8ed3384dd":{"statistic":{"failed":0,"broken":0,"skipped":0,"passed":1,"unknown":0,"total":1},"items":[{"uid":"b4fb4f315f79f86f","reportUrl":"https://Rustam-Z.github.io/disney-test-api-taf/28//#testresult/b4fb4f315f79f86f","status":"passed","time":{"start":1686279534362,"stop":1686279534533,"duration":171}}]},"05a8145250f346edc0d606e0c48f3582":{"statistic":{"failed":0,"broken":0,"skipped":0,"passed":1,"unknown":0,"total":1},"items":[{"uid":"99e47260232d31b4","reportUrl":"https://Rustam-Z.github.io/disney-test-api-taf/28//#testresult/99e47260232d31b4","status":"passed","time":{"start":1686279707144,"stop":1686279707536,"duration":392}}]},"f79c952e76ed9687b8f998c7e63da77d":{"statistic":{"failed":0,"broken":0,"skipped":0,"passed":1,"unknown":0,"total":1},"items":[{"uid":"e0dabb610ac8d9a","reportUrl":"https://Rustam-Z.github.io/disney-test-api-taf/28//#testresult/e0dabb610ac8d9a","status":"passed","time":{"start":1686279550954,"stop":1686279550992,"duration":38}}]},"afef4957ca97fe4c0776e355e739e4b1":{"statistic":{"failed":0,"broken":0,"skipped":0,"passed":1,"unknown":0,"total":1},"items":[{"uid":"a062358caa7459df","reportUrl":"https://Rustam-Z.github.io/disney-test-api-taf/28//#testresult/a062358caa7459df","status":"passed","time":{"start":1686279540039,"stop":1686279541517,"duration":1478}}]},"b6133378a39e99524786d6ac62d04ced":{"statistic":{"failed":0,"broken":0,"skipped":0,"passed":1,"unknown":0,"total":1},"items":[{"uid":"36fb8eb8f383456a","reportUrl":"https://Rustam-Z.github.io/disney-test-api-taf/28//#testresult/36fb8eb8f383456a","status":"passed","time":{"start":1686279636631,"stop":1686279636680,"duration":49}}]},"d68eee6a586c4c6fa1e315c5d6045d82":{"statistic":{"failed":0,"broken":0,"skipped":0,"passed":1,"unknown":0,"total":1},"items":[{"uid":"361987c39a712ec7","reportUrl":"https://Rustam-Z.github.io/disney-test-api-taf/28//#testresult/361987c39a712ec7","status":"passed","time":{"start":1686279646332,"stop":1686279646533,"duration":201}}]},"7c0f6e93bc3f16ca8096d9223b2eebde":{"statistic":{"failed":0,"broken":0,"skipped":0,"passed":1,"unknown":0,"total":1},"items":[{"uid":"74dbe290257d8923","reportUrl":"https://Rustam-Z.github.io/disney-test-api-taf/28//#testresult/74dbe290257d8923","status":"passed","time":{"start":1686279710554,"stop":1686279711085,"duration":531}}]},"4a21683fd3f417be34a3b7758bf20fac":{"statistic":{"failed":0,"broken":0,"skipped":0,"passed":1,"unknown":0,"total":1},"items":[{"uid":"73c0f8c67f17d4cc","reportUrl":"https://Rustam-Z.github.io/disney-test-api-taf/28//#testresult/73c0f8c67f17d4cc","status":"passed","time":{"start":1686279706666,"stop":1686279706682,"duration":16}}]},"0cb49e1d38042bb85a238d99d2239890":{"statistic":{"failed":0,"broken":0,"skipped":0,"passed":1,"unknown":0,"total":1},"items":[{"uid":"4e30f34d948b43fb","reportUrl":"https://Rustam-Z.github.io/disney-test-api-taf/28//#testresult/4e30f34d948b43fb","status":"passed","time":{"start":1686279646902,"stop":1686279648187,"duration":1285}}]},"5da92d561873d022310eb64642b9111f":{"statistic":{"failed":0,"broken":0,"skipped":0,"passed":1,"unknown":0,"total":1},"items":[{"uid":"f213fc542a5d8d69","reportUrl":"https://Rustam-Z.github.io/disney-test-api-taf/28//#testresult/f213fc542a5d8d69","status":"passed","time":{"start":1686279714796,"stop":1686279715166,"duration":370}}]},"24ff0f6f0c9193d05095aeda39206c84":{"statistic":{"failed":0,"broken":0,"skipped":0,"passed":1,"unknown":0,"total":1},"items":[{"uid":"303ac34e9bb6ecf6","reportUrl":"https://Rustam-Z.github.io/disney-test-api-taf/28//#testresult/303ac34e9bb6ecf6","status":"passed","time":{"start":1686279644007,"stop":1686279645657,"duration":1650}}]},"235d061cabd6a569045dd2b9dff68442":{"statistic":{"failed":0,"broken":0,"skipped":0,"passed":1,"unknown":0,"total":1},"items":[{"uid":"ddb6ffcc40b64f1e","reportUrl":"https://Rustam-Z.github.io/disney-test-api-taf/28//#testresult/ddb6ffcc40b64f1e","status":"passed","time":{"start":1686279535350,"stop":1686279535388,"duration":38}}]},"f6ea310b17d093f60cafe79aa9bd91cb":{"statistic":{"failed":0,"broken":0,"skipped":0,"passed":1,"unknown":0,"total":1},"items":[{"uid":"52b0cf97b77c35b9","reportUrl":"https://Rustam-Z.github.io/disney-test-api-taf/28//#testresult/52b0cf97b77c35b9","status":"passed","time":{"start":1686279705916,"stop":1686279706002,"duration":86}}]},"9af86aeeaf1b5b35d481009be8a34594":{"statistic":{"failed":0,"broken":0,"skipped":0,"passed":1,"unknown":0,"total":1},"items":[{"uid":"917b18f620c7bc2c","reportUrl":"https://Rustam-Z.github.io/disney-test-api-taf/28//#testresult/917b18f620c7bc2c","status":"passed","time":{"start":1686279692211,"stop":1686279692988,"duration":777}}]},"7d7554c3f1ac717dde147eea95690877":{"statistic":{"failed":0,"broken":0,"skipped":0,"passed":1,"unknown":0,"total":1},"items":[{"uid":"c53f717f7bbbdb5f","reportUrl":"https://Rustam-Z.github.io/disney-test-api-taf/28//#testresult/c53f717f7bbbdb5f","status":"passed","time":{"start":1686279716885,"stop":1686279717962,"duration":1077}}]},"d816c45eb841902fa0e9e404dc84cbed":{"statistic":{"failed":0,"broken":0,"skipped":0,"passed":1,"unknown":0,"total":1},"items":[{"uid":"e6336b8571a944de","reportUrl":"https://Rustam-Z.github.io/disney-test-api-taf/28//#testresult/e6336b8571a944de","status":"passed","time":{"start":1686279713668,"stop":1686279714006,"duration":338}}]},"23bdc0e6ae43a9406a7673e2b4580496":{"statistic":{"failed":0,"broken":0,"skipped":0,"passed":1,"unknown":0,"total":1},"items":[{"uid":"f4f9d73679013e71","reportUrl":"https://Rustam-Z.github.io/disney-test-api-taf/28//#testresult/f4f9d73679013e71","status":"passed","time":{"start":1686279714009,"stop":1686279714363,"duration":354}}]},"f331ea8e7efded2ffb7d32a2391108cf":{"statistic":{"failed":0,"broken":0,"skipped":0,"passed":1,"unknown":0,"total":1},"items":[{"uid":"be5116d717e6401c","reportUrl":"https://Rustam-Z.github.io/disney-test-api-taf/28//#testresult/be5116d717e6401c","status":"passed","time":{"start":1686279697938,"stop":1686279697985,"duration":47}}]},"31105a61a624976ec0975ca55c4f402d":{"statistic":{"failed":0,"broken":0,"skipped":0,"passed":1,"unknown":0,"total":1},"items":[{"uid":"290bf3f1a82f7c9a","reportUrl":"https://Rustam-Z.github.io/disney-test-api-taf/28//#testresult/290bf3f1a82f7c9a","status":"passed","time":{"start":1686279551045,"stop":1686279551061,"duration":16}}]},"67d28ef5f6cbd4cff42ba6ed7bb2517b":{"statistic":{"failed":0,"broken":0,"skipped":0,"passed":1,"unknown":0,"total":1},"items":[{"uid":"45d60c494afc3615","reportUrl":"https://Rustam-Z.github.io/disney-test-api-taf/28//#testresult/45d60c494afc3615","status":"passed","time":{"start":1686279535639,"stop":1686279535676,"duration":37}}]},"ee36407de6dd37d2b5ee2e9c56b58867":{"statistic":{"failed":0,"broken":0,"skipped":0,"passed":1,"unknown":0,"total":1},"items":[{"uid":"a140be1feb18ae92","reportUrl":"https://Rustam-Z.github.io/disney-test-api-taf/28//#testresult/a140be1feb18ae92","status":"passed","time":{"start":1686279712026,"stop":1686279712491,"duration":465}}]},"f5e244c5942994d0ed89ca47797998af":{"statistic":{"failed":0,"broken":0,"skipped":0,"passed":1,"unknown":0,"total":1},"items":[{"uid":"a99eb7d149e2a62f","reportUrl":"https://Rustam-Z.github.io/disney-test-api-taf/28//#testresult/a99eb7d149e2a62f","status":"passed","time":{"start":1686279630641,"stop":1686279631539,"duration":898}}]},"a6d9f935183c26e4d355719ba5d2e157":{"statistic":{"failed":0,"broken":0,"skipped":0,"passed":1,"unknown":0,"total":1},"items":[{"uid":"9dfb67ed1f08f824","reportUrl":"https://Rustam-Z.github.io/disney-test-api-taf/28//#testresult/9dfb67ed1f08f824","status":"passed","time":{"start":1686279712969,"stop":1686279713316,"duration":347}}]},"b6baeaa0ec296c20c541502fd8170ea0":{"statistic":{"failed":0,"broken":0,"skipped":0,"passed":1,"unknown":0,"total":1},"items":[{"uid":"293e1cdc9f5012da","reportUrl":"https://Rustam-Z.github.io/disney-test-api-taf/28//#testresult/293e1cdc9f5012da","status":"passed","time":{"start":1686279718292,"stop":1686279719561,"duration":1269}}]},"e48bc8f36841345377db970c5c01b7f2":{"statistic":{"failed":0,"broken":0,"skipped":0,"passed":1,"unknown":0,"total":1},"items":[{"uid":"1ab6a33338bd3155","reportUrl":"https://Rustam-Z.github.io/disney-test-api-taf/28//#testresult/1ab6a33338bd3155","status":"passed","time":{"start":1686279555623,"stop":1686279555890,"duration":267}}]},"7111dedc81b64e23f17ba72fda0e4ca4":{"statistic":{"failed":0,"broken":0,"skipped":0,"passed":1,"unknown":0,"total":1},"items":[{"uid":"76ac30c2d05ed268","reportUrl":"https://Rustam-Z.github.io/disney-test-api-taf/28//#testresult/76ac30c2d05ed268","status":"passed","time":{"start":1686279706295,"stop":1686279706389,"duration":94}}]},"3007dacfba3fe9da1b789a85ff16677b":{"statistic":{"failed":0,"broken":0,"skipped":0,"passed":1,"unknown":0,"total":1},"items":[{"uid":"e05aca72a6379e2c","reportUrl":"https://Rustam-Z.github.io/disney-test-api-taf/28//#testresult/e05aca72a6379e2c","status":"passed","time":{"start":1686279537260,"stop":1686279537575,"duration":315}}]},"66389b59a964c63183c4b62ccf35bcda":{"statistic":{"failed":0,"broken":0,"skipped":0,"passed":1,"unknown":0,"total":1},"items":[{"uid":"ff17bcbb6e4dcf5e","reportUrl":"https://Rustam-Z.github.io/disney-test-api-taf/28//#testresult/ff17bcbb6e4dcf5e","status":"passed","time":{"start":1686279548336,"stop":1686279548414,"duration":78}}]},"10d865827a6f00f5ffd56d8c284a6c11":{"statistic":{"failed":0,"broken":0,"skipped":0,"passed":1,"unknown":0,"total":1},"items":[{"uid":"73ba0de7e369fa8a","reportUrl":"https://Rustam-Z.github.io/disney-test-api-taf/28//#testresult/73ba0de7e369fa8a","status":"passed","time":{"start":1686279708239,"stop":1686279708765,"duration":526}}]},"f570528147a05b363b6d677bb75b577c":{"statistic":{"failed":0,"broken":0,"skipped":0,"passed":1,"unknown":0,"total":1},"items":[{"uid":"5223cfbb6267e675","reportUrl":"https://Rustam-Z.github.io/disney-test-api-taf/28//#testresult/5223cfbb6267e675","status":"passed","time":{"start":1686279706648,"stop":1686279706663,"duration":15}}]},"428cfe7dc1c4967ccfdfd3b149c2c25a":{"statistic":{"failed":0,"broken":0,"skipped":0,"passed":1,"unknown":0,"total":1},"items":[{"uid":"d33544496e207fad","reportUrl":"https://Rustam-Z.github.io/disney-test-api-taf/28//#testresult/d33544496e207fad","status":"passed","time":{"start":1686279715169,"stop":1686279715185,"duration":16}}]},"6707fd56046c0ef15fe3a17602f57b53":{"statistic":{"failed":0,"broken":0,"skipped":0,"passed":1,"unknown":0,"total":1},"items":[{"uid":"c816d3c9103fbc83","reportUrl":"https://Rustam-Z.github.io/disney-test-api-taf/28//#testresult/c816d3c9103fbc83","status":"passed","time":{"start":1686279535186,"stop":1686279535235,"duration":49}}]},"f986e6a228b83793807141e3961b0ad4":{"statistic":{"failed":0,"broken":0,"skipped":0,"passed":1,"unknown":0,"total":1},"items":[{"uid":"3874903d3e738f82","reportUrl":"https://Rustam-Z.github.io/disney-test-api-taf/28//#testresult/3874903d3e738f82","status":"passed","time":{"start":1686279712551,"stop":1686279712605,"duration":54}}]},"2b3486e139d142db5e99df79bbbd05c1":{"statistic":{"failed":0,"broken":0,"skipped":0,"passed":1,"unknown":0,"total":1},"items":[{"uid":"187949ee9ee22b30","reportUrl":"https://Rustam-Z.github.io/disney-test-api-taf/28//#testresult/187949ee9ee22b30","status":"passed","time":{"start":1686279706685,"stop":1686279706702,"duration":17}}]},"3cb578fecb7102c6bbcf357f2b4c401d":{"statistic":{"failed":0,"broken":0,"skipped":0,"passed":1,"unknown":0,"total":1},"items":[{"uid":"a367283ad5535d54","reportUrl":"https://Rustam-Z.github.io/disney-test-api-taf/28//#testresult/a367283ad5535d54","status":"passed","time":{"start":1686279713319,"stop":1686279713665,"duration":346}}]},"98a99bc73972f7834798c39423c08429":{"statistic":{"failed":0,"broken":0,"skipped":0,"passed":1,"unknown":0,"total":1},"items":[{"uid":"d3178faa32186654","reportUrl":"https://Rustam-Z.github.io/disney-test-api-taf/28//#testresult/d3178faa32186654","status":"passed","time":{"start":1686279557881,"stop":1686279558220,"duration":339}}]},"c788272f3714f07fb7d56cb40c0f90f8":{"statistic":{"failed":0,"broken":0,"skipped":0,"passed":1,"unknown":0,"total":1},"items":[{"uid":"229cc67c5e3ed367","reportUrl":"https://Rustam-Z.github.io/disney-test-api-taf/28//#testresult/229cc67c5e3ed367","status":"passed","time":{"start":1686279549248,"stop":1686279549391,"duration":143}}]},"60e5b3d7731472e91a4d3fef954085f5":{"statistic":{"failed":0,"broken":0,"skipped":0,"passed":1,"unknown":0,"total":1},"items":[{"uid":"f359fb6b21f9e499","reportUrl":"https://Rustam-Z.github.io/disney-test-api-taf/28//#testresult/f359fb6b21f9e499","status":"passed","time":{"start":1686279696061,"stop":1686279696315,"duration":254}}]},"f3c03cea6f5520bed566de4a81d4ae7f":{"statistic":{"failed":0,"broken":0,"skipped":0,"passed":1,"unknown":0,"total":1},"items":[{"uid":"7c22378f5d9cc58a","reportUrl":"https://Rustam-Z.github.io/disney-test-api-taf/28//#testresult/7c22378f5d9cc58a","status":"passed","time":{"start":1686279550306,"stop":1686279550564,"duration":258}}]},"6041631ba85b0f5954ccfcb9d3e0eec3":{"statistic":{"failed":0,"broken":0,"skipped":0,"passed":1,"unknown":0,"total":1},"items":[{"uid":"290a68028eb97837","reportUrl":"https://Rustam-Z.github.io/disney-test-api-taf/28//#testresult/290a68028eb97837","status":"passed","time":{"start":1686279697988,"stop":1686279698998,"duration":1010}}]},"3892496dfe01fd6e518877af95e7e160":{"statistic":{"failed":0,"broken":0,"skipped":0,"passed":1,"unknown":0,"total":1},"items":[{"uid":"b683a25b861e2be2","reportUrl":"https://Rustam-Z.github.io/disney-test-api-taf/28//#testresult/b683a25b861e2be2","status":"passed","time":{"start":1686279535391,"stop":1686279535450,"duration":59}}]},"6229be4daaff65a350c44b7916b09044":{"statistic":{"failed":0,"broken":0,"skipped":0,"passed":1,"unknown":0,"total":1},"items":[{"uid":"9c038a990b635fdf","reportUrl":"https://Rustam-Z.github.io/disney-test-api-taf/28//#testresult/9c038a990b635fdf","status":"passed","time":{"start":1686279551683,"stop":1686279551727,"duration":44}}]},"03acca80c4375159690ee6961d69cf8c":{"statistic":{"failed":0,"broken":0,"skipped":0,"passed":1,"unknown":0,"total":1},"items":[{"uid":"d62352400dae6bf4","reportUrl":"https://Rustam-Z.github.io/disney-test-api-taf/28//#testresult/d62352400dae6bf4","status":"passed","time":{"start":1686279551730,"stop":1686279551770,"duration":40}}]},"69dc2f583a927cd9b1dd57c5453226bc":{"statistic":{"failed":0,"broken":0,"skipped":0,"passed":1,"unknown":0,"total":1},"items":[{"uid":"a1c310cfcd8dd2a9","reportUrl":"https://Rustam-Z.github.io/disney-test-api-taf/28//#testresult/a1c310cfcd8dd2a9","status":"passed","time":{"start":1686279693464,"stop":1686279693839,"duration":375}}]},"67db4974fee10683e6fca495f4d07eb4":{"statistic":{"failed":0,"broken":0,"skipped":0,"passed":1,"unknown":0,"total":1},"items":[{"uid":"95ac9087ad7c6152","reportUrl":"https://Rustam-Z.github.io/disney-test-api-taf/28//#testresult/95ac9087ad7c6152","status":"passed","time":{"start":1686279694202,"stop":1686279694500,"duration":298}}]},"1fb191f881ddca89779a75dd5d8dd45c":{"statistic":{"failed":0,"broken":0,"skipped":0,"passed":1,"unknown":0,"total":1},"items":[{"uid":"3199c9af201b2e35","reportUrl":"https://Rustam-Z.github.io/disney-test-api-taf/28//#testresult/3199c9af201b2e35","status":"passed","time":{"start":1686279554088,"stop":1686279554306,"duration":218}}]},"5851efd47ee16f7b39e56801a34f800c":{"statistic":{"failed":0,"broken":0,"skipped":0,"passed":1,"unknown":0,"total":1},"items":[{"uid":"6e9005e56ba7420d","reportUrl":"https://Rustam-Z.github.io/disney-test-api-taf/28//#testresult/6e9005e56ba7420d","status":"passed","time":{"start":1686279551868,"stop":1686279551907,"duration":39}}]},"12ae7f849e0ffa95f100fe359bb37505":{"statistic":{"failed":0,"broken":0,"skipped":0,"passed":1,"unknown":0,"total":1},"items":[{"uid":"1ecac28b5e567314","reportUrl":"https://Rustam-Z.github.io/disney-test-api-taf/28//#testresult/1ecac28b5e567314","status":"passed","time":{"start":1686279635050,"stop":1686279635455,"duration":405}}]},"002a179b9fbc82fbe072a282283382a1":{"statistic":{"failed":0,"broken":0,"skipped":0,"passed":1,"unknown":0,"total":1},"items":[{"uid":"7210733d87f5faa1","reportUrl":"https://Rustam-Z.github.io/disney-test-api-taf/28//#testresult/7210733d87f5faa1","status":"passed","time":{"start":1686279634558,"stop":1686279634911,"duration":353}}]},"48d7d21132d477ed4d86344ba2aadef3":{"statistic":{"failed":0,"broken":0,"skipped":0,"passed":1,"unknown":0,"total":1},"items":[{"uid":"10a14bbb7cc96939","reportUrl":"https://Rustam-Z.github.io/disney-test-api-taf/28//#testresult/10a14bbb7cc96939","status":"passed","time":{"start":1686279536730,"stop":1686279537002,"duration":272}}]},"655ede60f5128fd98c443ea4e3657409":{"statistic":{"failed":0,"broken":0,"skipped":0,"passed":1,"unknown":0,"total":1},"items":[{"uid":"593ce98acd850baf","reportUrl":"https://Rustam-Z.github.io/disney-test-api-taf/28//#testresult/593ce98acd850baf","status":"passed","time":{"start":1686279535237,"stop":1686279535286,"duration":49}}]},"5a67a659107d4c805254f2109f204bc9":{"statistic":{"failed":0,"broken":0,"skipped":0,"passed":1,"unknown":0,"total":1},"items":[{"uid":"c12e12f0dd670e77","reportUrl":"https://Rustam-Z.github.io/disney-test-api-taf/28//#testresult/c12e12f0dd670e77","status":"passed","time":{"start":1686279636683,"stop":1686279638213,"duration":1530}}]},"b71274e4196616804cefb425d19ef8a0":{"statistic":{"failed":0,"broken":0,"skipped":0,"passed":1,"unknown":0,"total":1},"items":[{"uid":"81463c23d611c574","reportUrl":"https://Rustam-Z.github.io/disney-test-api-taf/28//#testresult/81463c23d611c574","status":"passed","time":{"start":1686279714404,"stop":1686279714420,"duration":16}}]},"5053bc0d0f4e55ccf92ac5d486a478e4":{"statistic":{"failed":0,"broken":0,"skipped":0,"passed":1,"unknown":0,"total":1},"items":[{"uid":"d5a6f66367b7733a","reportUrl":"https://Rustam-Z.github.io/disney-test-api-taf/28//#testresult/d5a6f66367b7733a","status":"passed","time":{"start":1686279555553,"stop":1686279555620,"duration":67}}]},"4708611153439da6544eaac17c0cf68d":{"statistic":{"failed":0,"broken":0,"skipped":0,"passed":1,"unknown":0,"total":1},"items":[{"uid":"77c09d3afe237eb","reportUrl":"https://Rustam-Z.github.io/disney-test-api-taf/28//#testresult/77c09d3afe237eb","status":"passed","time":{"start":1686279543684,"stop":1686279544738,"duration":1054}}]},"3894fcce3f68e5e69c0bee633c9d8a86":{"statistic":{"failed":0,"broken":0,"skipped":0,"passed":1,"unknown":0,"total":1},"items":[{"uid":"8aeabf14c8fd2f58","reportUrl":"https://Rustam-Z.github.io/disney-test-api-taf/28//#testresult/8aeabf14c8fd2f58","status":"passed","time":{"start":1686279696616,"stop":1686279697514,"duration":898}}]},"ea3597c7f968be848e7065f71e02a1e7":{"statistic":{"failed":0,"broken":0,"skipped":0,"passed":1,"unknown":0,"total":1},"items":[{"uid":"57242118fc76b691","reportUrl":"https://Rustam-Z.github.io/disney-test-api-taf/28//#testresult/57242118fc76b691","status":"passed","time":{"start":1686279551029,"stop":1686279551043,"duration":14}}]},"84cd745b097f1308ac2fcd2e4ff8bae3":{"statistic":{"failed":0,"broken":0,"skipped":0,"passed":1,"unknown":0,"total":1},"items":[{"uid":"8a62815a09d66ef2","reportUrl":"https://Rustam-Z.github.io/disney-test-api-taf/28//#testresult/8a62815a09d66ef2","status":"passed","time":{"start":1686279706005,"stop":1686279706100,"duration":95}}]},"a509c9fd8d33a22f4ce68a473db8236e":{"statistic":{"failed":0,"broken":0,"skipped":0,"passed":1,"unknown":0,"total":1},"items":[{"uid":"349c3b5745d16391","reportUrl":"https://Rustam-Z.github.io/disney-test-api-taf/28//#testresult/349c3b5745d16391","status":"passed","time":{"start":1686279633960,"stop":1686279634024,"duration":64}}]},"f4473e1fba61b7e6af436fffd26cd359":{"statistic":{"failed":0,"broken":0,"skipped":0,"passed":1,"unknown":0,"total":1},"items":[{"uid":"29d8f12232aa4f8e","reportUrl":"https://Rustam-Z.github.io/disney-test-api-taf/28//#testresult/29d8f12232aa4f8e","status":"passed","time":{"start":1686279551911,"stop":1686279552135,"duration":224}}]},"2c21fafd43869d5d3f0add336a25b57b":{"statistic":{"failed":0,"broken":0,"skipped":0,"passed":1,"unknown":0,"total":1},"items":[{"uid":"27e6459b9af9e0b9","reportUrl":"https://Rustam-Z.github.io/disney-test-api-taf/28//#testresult/27e6459b9af9e0b9","status":"passed","time":{"start":1686279711159,"stop":1686279711955,"duration":796}}]},"1fbb58bfafba2ceb0a6a269b9f18a49e":{"statistic":{"failed":0,"broken":0,"skipped":0,"passed":1,"unknown":0,"total":1},"items":[{"uid":"3b72873b62f358e1","reportUrl":"https://Rustam-Z.github.io/disney-test-api-taf/28//#testresult/3b72873b62f358e1","status":"passed","time":{"start":1686279553523,"stop":1686279553840,"duration":317}}]},"ef095a374d66c9b992c05247e1d3edb6":{"statistic":{"failed":0,"broken":0,"skipped":0,"passed":1,"unknown":0,"total":1},"items":[{"uid":"450d8649d9fcc46c","reportUrl":"https://Rustam-Z.github.io/disney-test-api-taf/28//#testresult/450d8649d9fcc46c","status":"passed","time":{"start":1686279632884,"stop":1686279633144,"duration":260}}]},"e8296b4daa97b73bd53ae3a6852d60e5":{"statistic":{"failed":0,"broken":0,"skipped":0,"passed":1,"unknown":0,"total":1},"items":[{"uid":"cf3ff7be9f19e57","reportUrl":"https://Rustam-Z.github.io/disney-test-api-taf/28//#testresult/cf3ff7be9f19e57","status":"passed","time":{"start":1686279699449,"stop":1686279699721,"duration":272}}]},"c1cacc030d5bdfd9375d4d83a065da9f":{"statistic":{"failed":0,"broken":0,"skipped":0,"passed":1,"unknown":0,"total":1},"items":[{"uid":"f452db15e6da9db0","reportUrl":"https://Rustam-Z.github.io/disney-test-api-taf/28//#testresult/f452db15e6da9db0","status":"passed","time":{"start":1686279549812,"stop":1686279549959,"duration":147}}]},"a42c4eb31247b9283257c7f4ed00fc93":{"statistic":{"failed":0,"broken":0,"skipped":0,"passed":1,"unknown":0,"total":1},"items":[{"uid":"84e2e5e55487ca8b","reportUrl":"https://Rustam-Z.github.io/disney-test-api-taf/28//#testresult/84e2e5e55487ca8b","status":"passed","time":{"start":1686279535680,"stop":1686279535894,"duration":214}}]},"1cb69db663a35ab9357226a65b254ac3":{"statistic":{"failed":0,"broken":0,"skipped":0,"passed":1,"unknown":0,"total":1},"items":[{"uid":"652359fd73116fb7","reportUrl":"https://Rustam-Z.github.io/disney-test-api-taf/28//#testresult/652359fd73116fb7","status":"passed","time":{"start":1686279556727,"stop":1686279557061,"duration":334}}]},"b799b98c469b85aff6f3fc6382b89597":{"statistic":{"failed":0,"broken":0,"skipped":0,"passed":1,"unknown":0,"total":1},"items":[{"uid":"3744bb0cb2a2b4fc","reportUrl":"https://Rustam-Z.github.io/disney-test-api-taf/28//#testresult/3744bb0cb2a2b4fc","status":"passed","time":{"start":1686279546586,"stop":1686279547899,"duration":1313}}]},"3b375a377c9e58e0bea6e981f88a1021":{"statistic":{"failed":0,"broken":0,"skipped":0,"passed":1,"unknown":0,"total":1},"items":[{"uid":"7680b4324246d6ee","reportUrl":"https://Rustam-Z.github.io/disney-test-api-taf/28//#testresult/7680b4324246d6ee","status":"passed","time":{"start":1686279558656,"stop":1686279558785,"duration":129}}]},"9c63574495ec4e406ce8061d7352d9ac":{"statistic":{"failed":0,"broken":0,"skipped":0,"passed":1,"unknown":0,"total":1},"items":[{"uid":"494af79ddaf3491e","reportUrl":"https://Rustam-Z.github.io/disney-test-api-taf/28//#testresult/494af79ddaf3491e","status":"passed","time":{"start":1686279535556,"stop":1686279535594,"duration":38}}]},"9a75a00374915562da869b5242a773ab":{"statistic":{"failed":0,"broken":0,"skipped":0,"passed":1,"unknown":0,"total":1},"items":[{"uid":"443a8421ed638cfd","reportUrl":"https://Rustam-Z.github.io/disney-test-api-taf/28//#testresult/443a8421ed638cfd","status":"passed","time":{"start":1686279549499,"stop":1686279549582,"duration":83}}]},"03e22c157fcd0a3b05bc42bcd989b687":{"statistic":{"failed":0,"broken":0,"skipped":0,"passed":1,"unknown":0,"total":1},"items":[{"uid":"fdbce106ec1eb6f5","reportUrl":"https://Rustam-Z.github.io/disney-test-api-taf/28//#testresult/fdbce106ec1eb6f5","status":"passed","time":{"start":1686279631975,"stop":1686279632561,"duration":586}}]},"c801b1051031d1110b8ebcd173b3299a":{"statistic":{"failed":0,"broken":0,"skipped":0,"passed":1,"unknown":0,"total":1},"items":[{"uid":"3a2c72aa8e48fa3d","reportUrl":"https://Rustam-Z.github.io/disney-test-api-taf/28//#testresult/3a2c72aa8e48fa3d","status":"passed","time":{"start":1686279551154,"stop":1686279551203,"duration":49}}]},"825089b9f552678925d4b63dabda5c1e":{"statistic":{"failed":0,"broken":0,"skipped":0,"passed":1,"unknown":0,"total":1},"items":[{"uid":"1cae4c46c623df50","reportUrl":"https://Rustam-Z.github.io/disney-test-api-taf/28//#testresult/1cae4c46c623df50","status":"passed","time":{"start":1686279552474,"stop":1686279552725,"duration":251}}]},"86d4f8a8403340304fb982e8da8aee0f":{"statistic":{"failed":0,"broken":0,"skipped":0,"passed":1,"unknown":0,"total":1},"items":[{"uid":"dc6ae8de0ae53bc1","reportUrl":"https://Rustam-Z.github.io/disney-test-api-taf/28//#testresult/dc6ae8de0ae53bc1","status":"passed","time":{"start":1686279535102,"stop":1686279535116,"duration":14}}]},"16ef2496500dc413a908ca6d4faa1dca":{"statistic":{"failed":0,"broken":0,"skipped":0,"passed":1,"unknown":0,"total":1},"items":[{"uid":"7893b29bbb89916f","reportUrl":"https://Rustam-Z.github.io/disney-test-api-taf/28//#testresult/7893b29bbb89916f","status":"passed","time":{"start":1686279552410,"stop":1686279552471,"duration":61}}]},"ab3ab4c1e517bc7a74b3067746fbd247":{"statistic":{"failed":0,"broken":0,"skipped":0,"passed":1,"unknown":0,"total":1},"items":[{"uid":"2060666d964f4139","reportUrl":"https://Rustam-Z.github.io/disney-test-api-taf/28//#testresult/2060666d964f4139","status":"passed","time":{"start":1686279533780,"stop":1686279533936,"duration":156}}]},"ed230b4bebe5b34c92f21ab2d6fe810c":{"statistic":{"failed":0,"broken":0,"skipped":0,"passed":1,"unknown":0,"total":1},"items":[{"uid":"bbaa5c91ec564212","reportUrl":"https://Rustam-Z.github.io/disney-test-api-taf/28//#testresult/bbaa5c91ec564212","status":"passed","time":{"start":1686279551291,"stop":1686279551333,"duration":42}}]},"a40f55f0d3f8c6862b15f58ec06a6ebe":{"statistic":{"failed":0,"broken":0,"skipped":0,"passed":1,"unknown":0,"total":1},"items":[{"uid":"63a6f1798d5e30a7","reportUrl":"https://Rustam-Z.github.io/disney-test-api-taf/28//#testresult/63a6f1798d5e30a7","status":"passed","time":{"start":1686279706546,"stop":1686279706646,"duration":100}}]},"9a97ee731469ba9e9471f14540164212":{"statistic":{"failed":0,"broken":0,"skipped":0,"passed":1,"unknown":0,"total":1},"items":[{"uid":"de02ae8377ce6874","reportUrl":"https://Rustam-Z.github.io/disney-test-api-taf/28//#testresult/de02ae8377ce6874","status":"passed","time":{"start":1686279556157,"stop":1686279556438,"duration":281}}]},"5e03d82d0da49b95cd69a0d292dadc84":{"statistic":{"failed":0,"broken":0,"skipped":0,"passed":1,"unknown":0,"total":1},"items":[{"uid":"c84aa9d295f8e3f1","reportUrl":"https://Rustam-Z.github.io/disney-test-api-taf/28//#testresult/c84aa9d295f8e3f1","status":"passed","time":{"start":1686279720691,"stop":1686279721855,"duration":1164}}]},"ad9eba398a7a595b61893be0918339b7":{"statistic":{"failed":0,"broken":0,"skipped":0,"passed":1,"unknown":0,"total":1},"items":[{"uid":"fd50438f5611847","reportUrl":"https://Rustam-Z.github.io/disney-test-api-taf/28//#testresult/fd50438f5611847","status":"passed","time":{"start":1686279551063,"stop":1686279551078,"duration":15}}]},"3511570d8555303423ef745b3a3432f8":{"statistic":{"failed":0,"broken":0,"skipped":0,"passed":1,"unknown":0,"total":1},"items":[{"uid":"8741d979360c49e2","reportUrl":"https://Rustam-Z.github.io/disney-test-api-taf/28//#testresult/8741d979360c49e2","status":"passed","time":{"start":1686279714366,"stop":1686279714381,"duration":15}}]},"b4753cd6f50785632e4c9436c3aae3ec":{"statistic":{"failed":0,"broken":0,"skipped":0,"passed":1,"unknown":0,"total":1},"items":[{"uid":"4ec723c560136499","reportUrl":"https://Rustam-Z.github.io/disney-test-api-taf/28//#testresult/4ec723c560136499","status":"passed","time":{"start":1686279535135,"stop":1686279535150,"duration":15}}]},"43f550a97efb5f6ff6e21633afa61185":{"statistic":{"failed":0,"broken":0,"skipped":0,"passed":1,"unknown":0,"total":1},"items":[{"uid":"dac7fbdc77077beb","reportUrl":"https://Rustam-Z.github.io/disney-test-api-taf/28//#testresult/dac7fbdc77077beb","status":"passed","time":{"start":1686279559419,"stop":1686279623949,"duration":64530}}]},"e4b1ecfc43c20c2534749d15b846779a":{"statistic":{"failed":0,"broken":0,"skipped":0,"passed":1,"unknown":0,"total":1},"items":[{"uid":"b8ed48c18be25296","reportUrl":"https://Rustam-Z.github.io/disney-test-api-taf/28//#testresult/b8ed48c18be25296","status":"passed","time":{"start":1686279538364,"stop":1686279538637,"duration":273}}]},"6028873488e1b6e1ff93043975222fd1":{"statistic":{"failed":0,"broken":0,"skipped":0,"passed":1,"unknown":0,"total":1},"items":[{"uid":"6d3030206e95d727","reportUrl":"https://Rustam-Z.github.io/disney-test-api-taf/28//#testresult/6d3030206e95d727","status":"passed","time":{"start":1686279551817,"stop":1686279551865,"duration":48}}]},"0b608d7e8e29e5914cdfed871aca0f9f":{"statistic":{"failed":0,"broken":0,"skipped":0,"passed":1,"unknown":0,"total":1},"items":[{"uid":"c951cf00f89b46f3","reportUrl":"https://Rustam-Z.github.io/disney-test-api-taf/28//#testresult/c951cf00f89b46f3","status":"passed","time":{"start":1686279551774,"stop":1686279551813,"duration":39}}]},"04df3e4f0f784dc73971ae296e3d67cd":{"statistic":{"failed":0,"broken":0,"skipped":0,"passed":1,"unknown":0,"total":1},"items":[{"uid":"473b41d4f1d5b61e","reportUrl":"https://Rustam-Z.github.io/disney-test-api-taf/28//#testresult/473b41d4f1d5b61e","status":"passed","time":{"start":1686279634335,"stop":1686279634555,"duration":220}}]},"63b0d010bc214a3e532ea2aafee62349":{"statistic":{"failed":0,"broken":0,"skipped":0,"passed":1,"unknown":0,"total":1},"items":[{"uid":"779c9b157251395a","reportUrl":"https://Rustam-Z.github.io/disney-test-api-taf/28//#testresult/779c9b157251395a","status":"passed","time":{"start":1686279535512,"stop":1686279535552,"duration":40}}]}}